aipalette_nlp/__init__.py
aipalette_nlp/preprocessing/__init__.py
aipalette_nlp/preprocessing/_clean_text.py
aipalette_nlp/preprocessing/_detect_lang.py
aipalette_nlp/preprocessing/_extract_hashtags_and_remove_hashtags.py
aipalette_nlp/preprocessing/_fix_fonts.py
aipalette_nlp/preprocessing/_remove_stopwords.py
aipalette_nlp/preprocessing/_replace_hashtags.py
aipalette_nlp/preprocessing/_replace_mentions.py
aipalette_nlp/preprocessing/_replace_phonenumber.py
aipalette_nlp/preprocessing/_replace_url.py
aipalette_nlp/tokenizer/__init__.py
aipalette_nlp/tokenizer/_word_tokenize.py
aipalette_nlp/tokenizer/pyarabic/__init__.py
aipalette_nlp/tokenizer/pyarabic/stack.py
aipalette_nlp/tokenizer/pyarabic/tokenizer.py
aipalette_nlp/tokenizer/pykotokenizer/__init__.py
aipalette_nlp/tokenizer/pykotokenizer/ko_spacing.py
aipalette_nlp-0.1.0.dist-info/LICENSE
aipalette_nlp-0.1.0.dist-info/METADATA
aipalette_nlp-0.1.0.dist-info/WHEEL
aipalette_nlp-0.1.0.dist-info/dependency_links.txt
aipalette_nlp-0.1.0.dist-info/top_level.txt
aipalette_nlp-0.1.0.dist-info/RECORD
