Metadata-Version: 2.1
Name: aipalette-nlp
Version: 0.1.0
Summary: Ai Palette NLP toolkit
Home-page: https://bitbucket.org/aipalettepermanent/aipalettenlp-package/src/ritvik-nlp/
Author: Ai Palette
Author-email: ritvik@aipalette.com
Project-URL: Bug Tracker, https://bitbucket.org/aipalettepermanent/aipalettenlp-package/src/ritvik-nlp/issues
Classifier: Programming Language :: Python :: 3
Classifier: License :: OSI Approved :: MIT License
Classifier: Operating System :: OS Independent
Requires-Python: >=3.8
License-File: LICENSE
Requires-Dist: setuptools (>=42)
Requires-Dist: wheel
Requires-Dist: nltk (==3.7)
Requires-Dist: fastai (==2.7.9)
Requires-Dist: Janome (==0.4.2)
Requires-Dist: jieba (==0.42.1)
Requires-Dist: numpy (==1.24.2)
Requires-Dist: emoji (==2.0.0)
Requires-Dist: pythainlp (==3.1.1)
Requires-Dist: torch (==1.12.1)
Requires-Dist: SoMaJo (==2.2.3)
Requires-Dist: pyvi (==0.1.1)
Requires-Dist: konlpy (==0.6.0)
Requires-Dist: langcodes (==3.3.0)
Requires-Dist: langid (==1.1.6)
Requires-Dist: language-data (==1.1)
